{
    "past": {
        "1.0": [
            {
                "name": "구선아",
                "contact": "son_ja_neun"
            },
            {
                "name": "김선재",
                "contact": "ssunj"
            },
            {
                "name": "박선정",
                "contact": "soft_tofu_91"
            },
            {
                "name": "백혜정",
                "contact": "haej.paik"
            },
            {
                "name": "이예연",
                "contact": "threecircles.kr"
            },
            {
                "name": "이은지",
                "contact": "ongjalee"
            },
            {
                "name": "조유리",
                "contact": "juju_the_yuri"
            },
            {
                "name": "조효원",
                "contact": "hyowon_cr"
            }
        ],
        "2.0": [
            {
                "name": "방정인",
                "contact": "archvang"
            },
            {
                "name": "백민지",
                "contact": "bk_noname"
            },
            {
                "name": "이자연",
                "contact": "jayeonature_eee"
            }
        ],
        "3.0": [
            {
                "name": "김수민",
                "contact": "soominmaseng"
            },
            {
                "name": "박신우",
                "contact": "paper_press"
            },
            {
                "name": "방성원",
                "contact": "srachelbang"
            },
            {
                "name": "유성민",
                "contact": "joomidoomi"
            },
            {
                "name": "조소희",
                "contact": "Wrkjoewrk"
            }
        ],
        "4.0": [
            {
                "name": "김나해",
                "contact": "nahae.k"
            },
            {
                "name": "김신영",
                "contact": "newwwww_s"
            },
            {
                "name": "이혜영",
                "contact": "heyoii__buddhist"
            }
        ],
        "5.0": [
            {
                "name": "이주희",
                "contact": "jooo.h_"
            },
            {
                "name": "정의미",
                "contact": "uimijeong"
            },
            {
                "name": "정재연",
                "contact": "jaey.jung"
            },
            {
                "name": "박정수",
                "contact": "marxil_park_"
            },
            {
                "name": "채보영",
                "contact": "neulb00"
            },
            {
                "name": "최정은",
                "contact": "cjngn"
            }
        ],
        "6.0": [
            {
                "name": "김동민",
                "contact": "fly__to__the__moon"
            },
            {
                "name": "변아영",
                "contact": "08bay97"
            },
            {
                "name": "윤예림",
                "contact": "yoon_yerim0v0"
            },
            {
                "name": "인현진",
                "contact": "ennzn"
            }
        ],
        "7.0": [
            {
                "name": "박수경",
                "contact": "gnuykus"
            },
            {
                "name": "박정원",
                "contact": "ba.re.ul"
            },
            {
                "name": "오예원",
                "contact": "snoypw"
            },
            {
                "name": "정효은",
                "contact": "hyoeunij"
            }
        ],
        "8.0": [
            {
                "name": "전지우",
                "contact": "636x939"
            },
            {
                "name": "최세은",
                "contact": "sennnnc"
            },
            {
                "name": "조혜민",
                "contact": "mon.typo"
            },
            {
                "name": "유영서",
                "contact": "0_0suh_"
            },
            {
                "name": "박다영",
                "contact": "daundaun11"
            },
            {
                "name": "소혜린",
                "contact": "s_slinns"
            },
            {
                "name": "김혜리",
                "contact": "hyereemoly"
            },
            {
                "name": "이진실",
                "contact": "truth._.lee__"
            }
        ],
        "9.0": [
            {
                "name": "임수진",
                "contact": "im_sujin816"
            },
            {
                "name": "김도아",
                "contact": "kissdeerr"
            },
            {
                "name": "이율리",
                "contact": "yulaylist"
            },
            {
                "name": "박상아",
                "contact": "thereis.future"
            },
            {
                "name": "권윤",
                "contact": "rnjsdbs_"
            },
            {
                "name": "유지율",
                "contact": "ujiually"
            },
            {
                "name": "김예인",
                "contact": "rla_dPdls615"
            }
        ],
        "10.0": [
            {
                "name": "김민채",
                "contact": "minn_works"
            },
            {
                "name": "윤주향",
                "contact": "puddinnnn00"
            },
            {
                "name": "김채영",
                "contact": "hxuef"
            },
            {
                "name": "이채영",
                "contact": "cosmicylee"
            }
        ]
    },
    "active": {
        "11.0": [
            {
                "name": "김한슬",
                "contact": "hans__sans"
            },
            {
                "name": "손다현",
                "contact": "xondhn"
            },
            {
                "name": "김유민",
                "contact": "yu.min_k"
            },
            {
                "name": "강유림",
                "contact": "yk_playground"
            },
            {
                "name": "장서진",
                "contact": "jinni5l"
            },
            {
                "name": "김민지",
                "contact": "minzz_2i2"
            }
        ],
        "12.0": [
            {
                "name": "한미리",
                "contact": "rniri_"
            },
            {
                "name": "김예진",
                "contact": "yejinnnk"
            },
            {
                "name": "이민서",
                "contact": "minsarchive_1"
            },
            {
                "name": "윤태희",
                "contact": "happ_heeist"
            },
            {
                "name": "두민영",
                "contact": "60.3.1"
            },
            {
                "name": "강수아",
                "contact": "workangsua"
            },
            {
                "name": "한유민",
                "contact": "what.youmean"
            },
            {
                "name": "최정안",
                "contact": "7eong7n"
            }
        ]
    }
}
